state_machine/__init__.py
state_machine/backends.py
state_machine/base.py
state_machine/core.py
state_machine/exceptions.py
state_machine/py.typed
state_machine/utils.py
state_machine_2-0.2.4.dist-info/LICENSE
state_machine_2-0.2.4.dist-info/METADATA
state_machine_2-0.2.4.dist-info/WHEEL
state_machine_2-0.2.4.dist-info/top_level.txt
state_machine_2-0.2.4.dist-info/RECORD
