Metadata-Version: 2.1
Name: state-machine-2
Version: 0.2.4
Summary: a state machine that support multi process
Home-page: https://github.com/ramwin/state-machine
Author: Xiang Wang
Author-email: ramwin@qq.com
License: UNKNOWN
Platform: UNKNOWN
Classifier: Programming Language :: Python :: 3
Requires-Python: >=3.7
License-File: LICENSE
Requires-Dist: redis
